htmlhelpers/__init__.py
htmlhelpers/htmlformat.py
htmlhelpers/htmlphrase.py
htmlhelpers/htmlstring.py
htmlhelpers/utils.py
htmlhelpers-0.1.1.dist-info/LICENSE.txt
htmlhelpers-0.1.1.dist-info/WHEEL
htmlhelpers-0.1.1.dist-info/METADATA
htmlhelpers-0.1.1.dist-info/RECORD
