Metadata-Version: 2.1
Name: htmlhelpers
Version: 0.1.1
Summary: Simple package that helps with creating html strings.
Home-page: https://github.com/steventimberman/htmlhelpers
License: MIT
Keywords: HTML,String Formatting
Author: steventimberman
Author-email: stevetimberman@gmail.com
Maintainer: steventimberman
Maintainer-email: stevetimberman@gmail.com
Requires-Python: >=3.7,<4.0
Classifier: License :: OSI Approved :: MIT License
Classifier: Programming Language :: Python :: 3
Classifier: Programming Language :: Python :: 3.7
Classifier: Programming Language :: Python :: 3.8
Project-URL: Repository, https://github.com/steventimberman/htmlhelpers
Project-URL: issues, https://github.com/steventimberman/htmlhelpers/issues
